cryprum/__init__.py
cryprum/__version__.py
cryprum/api.py
cryprum/asyncapi.py
cryprum/base.py
cryprum/exceptions.py
cryprum/helpers.py
tests/__init__.py
tests/test_client.py
cryprum-1.2.1.dist-info/METADATA
cryprum-1.2.1.dist-info/WHEEL
cryprum-1.2.1.dist-info/top_level.txt
cryprum-1.2.1.dist-info/RECORD
